vertopal/__init__.py
vertopal/enums.py
vertopal/exceptions.py
vertopal/settings.py
vertopal/types.py
vertopal/vertopal.py
vertopal/api/__init__.py
vertopal/api/converter.py
vertopal/api/credential.py
vertopal/api/interface.py
vertopal/api/response.py
vertopal/api/v1.py
vertopal/cli/__init__.py
vertopal/cli/api_manager.py
vertopal/cli/argument_parser.py
vertopal/cli/config_manager.py
vertopal/cli/conversion_manager.py
vertopal/io/__init__.py
vertopal/io/protocols.py
vertopal/io/adapters/__init__.py
vertopal/io/adapters/file.py
vertopal/io/adapters/memory.py
vertopal/io/adapters/stdio.py
vertopal/utils/__init__.py
vertopal/utils/config.py
vertopal/utils/dashboard_progress.py
vertopal/utils/data_wrappers.py
vertopal/utils/exception_handler.py
vertopal/utils/misc.py
vertopal/utils/prism.py
vertopal-2.1.0.dist-info/licenses/LICENSE
vertopal-2.1.0.dist-info/METADATA
vertopal-2.1.0.dist-info/WHEEL
vertopal-2.1.0.dist-info/entry_points.txt
vertopal-2.1.0.dist-info/top_level.txt
vertopal-2.1.0.dist-info/RECORD
