Metadata-Version: 2.4
Name: vertopal
Version: 2.1.0
Summary: Convert your files in terminal using Vertopal API
Home-page: https://github.com/vertopal/vertopal-cli
Author: Vertopal
Author-email: Vertopal <contact@vertopal.com>
License: MIT
Project-URL: Homepage, https://www.vertopal.com
Project-URL: Funding, https://www.vertopal.com/en/donate
Project-URL: Source, https://github.com/vertopal/vertopal-cli
Project-URL: Bug Tracker, https://github.com/vertopal/vertopal-cli/issues
Keywords: convert,file,vertopal,api,converter
Classifier: Programming Language :: Python :: 3
Classifier: Programming Language :: Python :: 3.9
Classifier: Intended Audience :: Developers
Classifier: Intended Audience :: End Users/Desktop
Classifier: Intended Audience :: Information Technology
Classifier: Intended Audience :: Science/Research
Classifier: Topic :: Software Development :: Libraries
Classifier: License :: OSI Approved :: MIT License
Requires-Python: >=3.9
License-File: LICENSE
Requires-Dist: requests>=2.28.2
Dynamic: author
Dynamic: home-page
Dynamic: license-file
Dynamic: requires-python
